Metadata-Version: 2.1
Name: scriptime
Version: 1.0.0
Summary: A Python library to notify when a script has finished running and providing insights such as run time, CPU and RAM usage, and more.
Author: Jake Strasler
Author-email: jstr36@gmail.com
License-File: LICENSE
Requires-Dist: psutil
Requires-Dist: simpleaudio
Requires-Dist: setuptools
